greedysub.py
greedysub-1.2.5.dist-info/LICENSE
greedysub-1.2.5.dist-info/METADATA
greedysub-1.2.5.dist-info/WHEEL
greedysub-1.2.5.dist-info/entry_points.txt
greedysub-1.2.5.dist-info/top_level.txt
greedysub-1.2.5.dist-info/RECORD
