Metadata-Version: 2.1
Name: greedysub
Version: 1.2.5
Summary: Reduce redundancy in dataset using greedy algorithms:
Home-page: https://github.com/agormp/greedysub
Author: Anders Gorm Pedersen
Author-email: agpe@dtu.dk
Classifier: Programming Language :: Python :: 3
Classifier: License :: OSI Approved :: GNU General Public License v3 (GPLv3)
Classifier: Operating System :: OS Independent
Requires-Python: >=3.7
License-File: LICENSE
Requires-Dist: pandas
